BCBvcl4pyAPI/AnsiStringLIB.cp310-win_amd64.pyd
BCBvcl4pyAPI/AnsiStringLIB.pyi
BCBvcl4pyAPI/BCBvcl4pyLIB.cp310-win_amd64.pyd
BCBvcl4pyAPI/BCBvcl4pyLIB.pyi
BCBvcl4pyAPI/HyperDynamicArrayLIB.cp310-win_amd64.pyd
BCBvcl4pyAPI/HyperDynamicArrayLIB.pyi
BCBvcl4pyAPI/TIniFileLIB.cp310-win_amd64.pyd
BCBvcl4pyAPI/TIniFileLIB.pyi
BCBvcl4pyAPI/TStreamLIB.cp310-win_amd64.pyd
BCBvcl4pyAPI/TStreamLIB.pyi
BCBvcl4pyAPI/TTimerLIB.cp310-win_amd64.pyd
BCBvcl4pyAPI/TTimerLIB.pyi
BCBvcl4pyAPI/__init__.py
BCBvcl4pyAPI/out/BCBvcl4pyAPI/AnsiStringLIB.pyi
BCBvcl4pyAPI/out/BCBvcl4pyAPI/BCBvcl4pyLIB.pyi
BCBvcl4pyAPI/out/BCBvcl4pyAPI/HyperDynamicArrayLIB.pyi
BCBvcl4pyAPI/out/BCBvcl4pyAPI/TIniFileLIB.pyi
BCBvcl4pyAPI/out/BCBvcl4pyAPI/TStreamLIB.pyi
BCBvcl4pyAPI/out/BCBvcl4pyAPI/TTimerLIB.pyi
bcbvcl4pyapi-1.2601.602.dist-info/licenses/LICENSE
bcbvcl4pyapi-1.2601.602.dist-info/METADATA
bcbvcl4pyapi-1.2601.602.dist-info/WHEEL
bcbvcl4pyapi-1.2601.602.dist-info/top_level.txt
bcbvcl4pyapi-1.2601.602.dist-info/RECORD
