Metadata-Version: 2.4
Name: BCBvcl4pyAPI
Version: 1.2601.602
Summary: BCBvcl4pyAPI Python package
Author-email: James Lin <tylin123@ms27.hinet.net>
License: Copyright (c) 2025 James Lin
Project-URL: Homepage, https://mis.gotech.biz
License-File: LICENSE
Requires-Dist: pymysql
Dynamic: license-file
